{
    "version": "2490",
    "description": "yuzu emulator early access",
    "homepage": "https://github.com/pineappleEA/pineapple-src",
    "checkver": {
        "url": "https://github.com/pineappleEA/pineapple-src/releases/latest",
        "re": "EA-(?<version>[\\d]+)"
    },
    "license": "GPLv2",
    "url": "https://github.com/pineappleEA/pineapple-src/releases/download/EA-2490/Windows-Yuzu-EA-2490.7z",
    "extract_dir": "yuzu-windows-msvc-early-access",
    "extract_to": "",
    "bin": "yuzu.exe",
    "shortcuts": [
        [
            "yuzu.exe",
            "Yuzu-EA"
        ]
    ],
    "persist": "user",
    "autoupdate": {
        "url": "https://github.com/pineappleEA/pineapple-src/releases/download/EA-$version/Windows-Yuzu-EA-$version.7z"
    },
    "hash": "fb028b5ac077badbc18f0bcf8cbc99d367871f9439a35cdb63edc22f8c078616"
}
